dubois/__init__.py
dubois/dubois.mplstyle
dubois/palettes.py
dubois/py.typed
dubois-0.1.0.dist-info/WHEEL
dubois-0.1.0.dist-info/METADATA
dubois-0.1.0.dist-info/RECORD
