Metadata-Version: 2.3
Name: dubois
Version: 0.1.0
Summary: Custom styles for W.E.B DuBois-inspired data visualizations
Author: David White
Author-email: David White <david.white@changemakerdata.nyc>
Requires-Python: >=3.13
